deelight/__init__.py
deelight/__main__.py
deelight/exceptions.py
deelight-1.3.2.dist-info/AUTHORS
deelight-1.3.2.dist-info/LICENSE
deelight-1.3.2.dist-info/METADATA
deelight-1.3.2.dist-info/WHEEL
deelight-1.3.2.dist-info/entry_points.txt
deelight-1.3.2.dist-info/pbr.json
deelight-1.3.2.dist-info/top_level.txt
deelight-1.3.2.dist-info/RECORD
