Metadata-Version: 2.1
Name: deelight
Version: 1.3.2
Summary: Daylight mode for Xiaomi Mi Yeelight bulbs and lights.
Home-page: https://github.com/codingjoe/yeelight-daylight
Author: Johannes Hoppe
Author-email: info@johanneshoppe.com
License: Apache-2
Keywords: light
Requires-Dist: yeelib (>=2.1.0)
Requires-Dist: pysolar (==0.7)
Requires-Dist: click
